mdx_embedly.py
mdx_embedly-0.4.0.dist-info/DESCRIPTION.rst
mdx_embedly-0.4.0.dist-info/METADATA
mdx_embedly-0.4.0.dist-info/RECORD
mdx_embedly-0.4.0.dist-info/WHEEL
mdx_embedly-0.4.0.dist-info/metadata.json
mdx_embedly-0.4.0.dist-info/top_level.txt
