Metadata-Version: 2.0
Name: mdx-embedly
Version: 0.4.0
Summary: Python Markdown extension for embeded url using Embedly
Home-page: https://github.com/yymm/mdx_embedly
Author: yymm
Author-email: yuya.yano.6260@gmail.com
License: MIT
Keywords: Markdown
Platform: UNKNOWN
Classifier: Development Status :: 5 - Production/Stable
Classifier: Intended Audience :: Developers
Classifier: Topic :: Text Processing :: Markup :: HTML
Classifier: License :: OSI Approved :: MIT License
Classifier: Programming Language :: Python :: 2
Classifier: Programming Language :: Python :: 2.7
Classifier: Programming Language :: Python :: 3
Classifier: Programming Language :: Python :: 3.4
Classifier: Programming Language :: Python :: 3.5
Requires-Dist: markdown
Provides-Extra: dev
Requires-Dist: check-manifest; extra == 'dev'
Provides-Extra: test
Requires-Dist: coverage; extra == 'test'
